hyperdx/opentelemetry/__init__.py
hyperdx/opentelemetry/baggage.py
hyperdx/opentelemetry/distro.py
hyperdx/opentelemetry/logs.py
hyperdx/opentelemetry/manual.py
hyperdx/opentelemetry/metrics.py
hyperdx/opentelemetry/options.py
hyperdx/opentelemetry/resource.py
hyperdx/opentelemetry/sampler.py
hyperdx/opentelemetry/trace.py
hyperdx/opentelemetry/version.py
hyperdx_opentelemetry-0.3.0.dist-info/LICENSE
hyperdx_opentelemetry-0.3.0.dist-info/METADATA
hyperdx_opentelemetry-0.3.0.dist-info/WHEEL
hyperdx_opentelemetry-0.3.0.dist-info/entry_points.txt
hyperdx_opentelemetry-0.3.0.dist-info/RECORD
