Metadata-Version: 2.3
Name: hyperdx-opentelemetry
Version: 0.3.0
Summary: HyperDX OpenTelemetry Distro for Python
Author: HyperDX
Author-email: support@hyperdx.io
Requires-Python: >=3.9
Classifier: Programming Language :: Python :: 3
Classifier: Programming Language :: Python :: 3.9
Classifier: Programming Language :: Python :: 3.10
Classifier: Programming Language :: Python :: 3.11
Classifier: Programming Language :: Python :: 3.12
Classifier: Programming Language :: Python :: 3.13
Requires-Dist: opentelemetry-api (==1.30.0)
Requires-Dist: opentelemetry-exporter-otlp (==1.30.0)
Requires-Dist: opentelemetry-instrumentation (==0.51b0)
Requires-Dist: opentelemetry-sdk (==1.30.0)
Requires-Dist: setuptools (>=75.8.0,<76.0.0)
